vimpy/__init__.py
vimpy/cv_vim.py
vimpy/predictiveness_measures.py
vimpy/spvim.py
vimpy/spvim_ic.py
vimpy/vim.py
vimpy/vimp_deviance.py
vimpy/vimp_regression.py
vimpy/vimpy_utils.py
vimpy-2.1.dist-info/LICENSE
vimpy-2.1.dist-info/METADATA
vimpy-2.1.dist-info/WHEEL
vimpy-2.1.dist-info/top_level.txt
vimpy-2.1.dist-info/RECORD
