Metadata-Version: 2.1
Name: vimpy
Version: 2.1
Summary: vimpy: perform inference on algorithm-agnostic variable importance in python
Home-page: https://github.com/bdwilliamson/vimpy
Author: Brian Williamson
Author-email: brianw26@uw.edu
License: MIT
Platform: UNKNOWN
Classifier: Programming Language :: Python :: 3.3
Classifier: License :: OSI Approved :: MIT License
Classifier: Operating System :: OS Independent
Requires-Dist: numpy
Requires-Dist: scipy
Requires-Dist: scipy.stats
